examples/__init__.py
examples/examplecommon.py
examples/parse_sample.py
examples/ping.txt
examples/ping_sample.py
examples/ping_win7.txt
pingparsing/__init__.py
pingparsing/__main__.py
pingparsing/__version__.py
pingparsing/_cmd_maker.py
pingparsing/_common.py
pingparsing/_interface.py
pingparsing/_logger.py
pingparsing/_parser.py
pingparsing/_pingparsing.py
pingparsing/_pingtransmitter.py
pingparsing/_stats.py
pingparsing/_typing.py
pingparsing/error.py
pingparsing/py.typed
pingparsing-1.4.2.dist-info/LICENSE
pingparsing-1.4.2.dist-info/METADATA
pingparsing-1.4.2.dist-info/WHEEL
pingparsing-1.4.2.dist-info/entry_points.txt
pingparsing-1.4.2.dist-info/top_level.txt
pingparsing-1.4.2.dist-info/RECORD
