Metadata-Version: 2.1
Name: pingparsing
Version: 1.4.2
Summary: pingparsing is a CLI-tool/Python-library parser and transmitter for the ping command.
Home-page: https://github.com/thombashi/pingparsing
Author: Tsuyoshi Hombashi
Author-email: tsuyoshi.hombashi@gmail.com
License: MIT License
Project-URL: Changelog, https://github.com/thombashi/pingparsing/blob/master/CHANGELOG.md
Project-URL: Documentation, https://pingparsing.rtfd.io/
Project-URL: Source, https://github.com/thombashi/pingparsing
Project-URL: Tracker, https://github.com/thombashi/pingparsing/issues
Keywords: cli,library,network,ping,parser,transmitter
Classifier: Development Status :: 5 - Production/Stable
Classifier: Environment :: Console
Classifier: Intended Audience :: Developers
Classifier: Intended Audience :: Information Technology
Classifier: Intended Audience :: Telecommunications Industry
Classifier: License :: OSI Approved :: MIT License
Classifier: Operating System :: MacOS
Classifier: Operating System :: Microsoft :: Windows
Classifier: Operating System :: POSIX
Classifier: Operating System :: POSIX :: Linux
Classifier: Programming Language :: Python :: 3
Classifier: Programming Language :: Python :: 3.7
Classifier: Programming Language :: Python :: 3.8
Classifier: Programming Language :: Python :: 3.9
Classifier: Programming Language :: Python :: 3.10
Classifier: Programming Language :: Python :: 3.11
Classifier: Programming Language :: Python :: 3.12
Classifier: Programming Language :: Python :: 3 :: Only
Classifier: Programming Language :: Python :: Implementation :: CPython
Classifier: Programming Language :: Python :: Implementation :: PyPy
Classifier: Topic :: Software Development :: Libraries
Classifier: Topic :: Software Development :: Libraries :: Python Modules
Classifier: Topic :: System :: Networking
Classifier: Topic :: System :: Networking :: Monitoring
Classifier: Topic :: Text Processing
Classifier: Typing :: Typed
Requires-Python: >=3.7
License-File: LICENSE
Requires-Dist: humanreadable<1,>=0.3
Requires-Dist: pyparsing<4,>=2.0.3
Requires-Dist: subprocrunner<3,>=1.2.2
Requires-Dist: typepy[datetime]<2,>=1.3.2
Provides-Extra: docs
Requires-Dist: sphinx_rtd_theme>=1.2.2; extra == "docs"
Requires-Dist: Sphinx>=2.4; extra == "docs"
Requires-Dist: subprocrunner; extra == "docs"
Provides-Extra: test
Requires-Dist: pytest>=6.0.1; extra == "test"
Requires-Dist: pytest-discord>=0.1.6; extra == "test"
Requires-Dist: pytest-md-report>=0.5; extra == "test"
Provides-Extra: cli
Requires-Dist: loguru<1,>=0.4.1; extra == "cli"
Requires-Dist: Pygments<3,>=2.1; extra == "cli"
